pyescher_remote/__init__.py
pyescher_remote/communicator.py
pyescher_remote/plotobject.py
pyescher_remote/remote_viewer.py
pyescher_remote-0.1.6.dist-info/METADATA
pyescher_remote-0.1.6.dist-info/WHEEL
pyescher_remote-0.1.6.dist-info/licenses/LICENSE
pyescher_remote-0.1.6.dist-info/RECORD
